nothing_cli/__init__.py
nothing_cli/constants.py
nothing_cli/filesystem.py
nothing_cli/localization/__init__.py
nothing_cli/localization/constants.py
nothing_cli/localization/en.json
nothing_cli/main.py
nothing_cli/models.py
nothing_cli/subcommand_shared.py
nothing_cli/tests/__init__.py
nothing_cli/tests/conftest.py
nothing_cli/tests/test_filesystem/__init__.py
nothing_cli/tests/test_filesystem/conftest.py
nothing_cli/tests/test_filesystem/test_collect_fancy_list_input.py
nothing_cli/tests/test_filesystem/test_deserialize_procedure_file.py
nothing_cli/tests/test_filesystem/test_friendly_prefix_for_path.py
nothing_cli/tests/test_filesystem/test_path_to_write_to.py
nothing_cli/tests/test_filesystem/test_procedure_location.py
nothing_cli/tests/test_filesystem/test_procedure_object_metadata.py
nothing_cli/tests/test_filesystem/test_state.py
nothing_cli/tests/test_main/__init__.py
nothing_cli/tests/test_main/conftest.py
nothing_cli/tests/test_main/test_do.py
nothing_cli/tests/test_main/test_drop.py
nothing_cli/tests/test_main/test_edit.py
nothing_cli/tests/test_main/test_info.py
nothing_cli/tests/test_main/test_init.py
nothing_cli/tests/test_main/test_ls.py
nothing_cli/tests/test_main/test_new.py
nothing_cli/tests/test_theatrics.py
nothing_cli/theatrics.py
nothing_cli/writer.py
nothing_cli-0.2.1.dist-info/entry_points.txt
nothing_cli-0.2.1.dist-info/WHEEL
nothing_cli-0.2.1.dist-info/METADATA
nothing_cli-0.2.1.dist-info/RECORD
