Metadata-Version: 2.1
Name: nothing-cli
Version: 0.2.1
Summary: Nothing helps coder be more smarter & less dumber.
License: MIT
Author: Ainsley McGrath
Author-email: mcgrath.ainsley@gmail.com
Requires-Python: >=3.6.1,<4.0.0
Classifier: License :: OSI Approved :: MIT License
Classifier: Programming Language :: Python :: 3
Classifier: Programming Language :: Python :: 3.7
Classifier: Programming Language :: Python :: 3.8
Requires-Dist: colorama (>=0.4.3,<0.5.0)
Requires-Dist: pydantic (>=1.4,<2.0)
Requires-Dist: python-slugify (>=4.0.0,<5.0.0)
Requires-Dist: ruamel.yaml (>=0.16.10,<0.17.0)
Requires-Dist: typer (>=0.1.0,<0.2.0)
Requires-Dist: typing-extensions (>=3.7.4,<4.0.0)
